ChemIITools/__init__.py
ChemIITools/_modidx.py
ChemIITools/clusters.py
ChemIITools/huckel.py
ChemIITools/kinetics.py
ChemIITools/optimisation.py
ChemIITools-0.0.4.dist-info/LICENSE
ChemIITools-0.0.4.dist-info/METADATA
ChemIITools-0.0.4.dist-info/WHEEL
ChemIITools-0.0.4.dist-info/entry_points.txt
ChemIITools-0.0.4.dist-info/top_level.txt
ChemIITools-0.0.4.dist-info/RECORD
