Metadata-Version: 2.1
Name: ChemIITools
Version: 0.0.4
Summary: Tools for Chemistry Part II programming
Home-page: https://github.com/KGrewal1/ChemIITools
Author: KGrewal1
Author-email: 45569241+KGrewal1@users.noreply.github.com
License: Apache Software License 2.0
Keywords: nbdev jupyter notebook python
Platform: UNKNOWN
Classifier: Development Status :: 4 - Beta
Classifier: Intended Audience :: Developers
Classifier: Natural Language :: English
Classifier: Programming Language :: Python :: 3.7
Classifier: Programming Language :: Python :: 3.8
Classifier: Programming Language :: Python :: 3.9
Classifier: Programming Language :: Python :: 3.10
Classifier: License :: OSI Approved :: Apache Software License
Requires-Python: >=3.7
License-File: LICENSE
Requires-Dist: numpy (>1.21)
Requires-Dist: rdkit (>=2022.9.3)
Requires-Dist: matplotlib (>3.5)
Requires-Dist: scipy (>1.7)
Requires-Dist: sympy (>1.7)
Provides-Extra: dev
